{"version":1,"resource":"file:///c%3A/Users/philip/Documents/PhilipProchazka.cz/DevCard-EN/assets/css/fonts/roboto-fontstyle.css","entries":[{"id":"SN3f.css","timestamp":1682091082333},{"id":"aUKK.css","timestamp":1682093851378},{"id":"VFVM.css","timestamp":1682098711969},{"id":"dINq.css","timestamp":1682101201306},{"id":"JvyO.css","timestamp":1682101257580},{"id":"dFQK.css","timestamp":1682101301700},{"id":"NVZI.css","timestamp":1682103644390},{"id":"kEOZ.css","timestamp":1682103877311},{"id":"e92C.css","timestamp":1682104103263},{"id":"YCsk.css","timestamp":1682104165442},{"id":"AX7Y.css","timestamp":1682104209365},{"id":"ZDum.css","timestamp":1682338526254},{"id":"tMsa.css","timestamp":1682338608971},{"id":"ORru.css","timestamp":1682341114964},{"id":"dTNz.css","timestamp":1682341137154},{"id":"Oqn1.css","timestamp":1682341156223},{"id":"yCUM.css","timestamp":1682341166265},{"id":"tMkZ.css","timestamp":1682341194789},{"id":"FXGe.css","timestamp":1682341233645},{"id":"o3DG.css","timestamp":1682341282091},{"id":"F058.css","timestamp":1682341345936}]}